Calculator/__init__.py
Calculator/simple_calculator.py
basic_calculator_avik-1.0.0.dist-info/METADATA
basic_calculator_avik-1.0.0.dist-info/WHEEL
basic_calculator_avik-1.0.0.dist-info/entry_points.txt
basic_calculator_avik-1.0.0.dist-info/top_level.txt
basic_calculator_avik-1.0.0.dist-info/RECORD
