Metadata-Version: 2.4
Name: basic_calculator_avik
Version: 1.0.0
Summary: This is a basic calculator package that can do additions, subtractions, etc.
Home-page: https://github.com/AvikSarkar0/Basic_Calculator.git
Author: avik-sarkar
Author-email: aviksarkar44545@gmail.com
Classifier: Programming Language :: Python :: 3
Classifier: License :: OSI Approved :: MIT License
Classifier: Operating System :: OS Independent
Requires-Python: >=3.12
Dynamic: author
Dynamic: author-email
Dynamic: classifier
Dynamic: description
Dynamic: description-content-type
Dynamic: home-page
Dynamic: requires-python
Dynamic: summary
